iddm/__init__.py
iddm/autoencoder/__init__.py
iddm/autoencoder/train.py
iddm/config/__init__.py
iddm/config/choices.py
iddm/config/model_list.py
iddm/config/setting.py
iddm/config/version.py
iddm/model/__init__.py
iddm/model/modules/__init__.py
iddm/model/modules/activation.py
iddm/model/modules/attention.py
iddm/model/modules/block.py
iddm/model/modules/conv.py
iddm/model/modules/ema.py
iddm/model/modules/module.py
iddm/model/networks/__init__.py
iddm/model/networks/base.py
iddm/model/networks/conditional.py
iddm/model/networks/cspdarkunet.py
iddm/model/networks/unet.py
iddm/model/networks/unet_cross_attn.py
iddm/model/networks/unet_flash_self_attn.py
iddm/model/networks/unet_slim.py
iddm/model/networks/unetv2.py
iddm/model/networks/sr/__init__.py
iddm/model/networks/sr/srv1.py
iddm/model/networks/vae/__init__.py
iddm/model/networks/vae/autoencoder.py
iddm/model/samples/__init__.py
iddm/model/samples/base.py
iddm/model/samples/ddim.py
iddm/model/samples/ddpm.py
iddm/model/samples/dpm2.py
iddm/model/samples/dpmpp.py
iddm/model/samples/plms.py
iddm/model/trainers/__init__.py
iddm/model/trainers/autoencoder.py
iddm/model/trainers/base.py
iddm/model/trainers/dm.py
iddm/model/trainers/sr.py
iddm/sr/__init__.py
iddm/sr/dataset.py
iddm/sr/demo.py
iddm/sr/interface.py
iddm/sr/train.py
iddm/tools/FID_calculator.py
iddm/tools/FID_calculator_plus.py
iddm/tools/__init__.py
iddm/tools/generate.py
iddm/tools/train.py
iddm/utils/__init__.py
iddm/utils/check.py
iddm/utils/checkpoint.py
iddm/utils/dataset.py
iddm/utils/initializer.py
iddm/utils/logger.py
iddm/utils/loss.py
iddm/utils/lr_scheduler.py
iddm/utils/metrics.py
iddm/utils/processing.py
iddm/utils/utils.py
iddm-1.3.1.dist-info/licenses/LICENSE
iddm-1.3.1.dist-info/METADATA
iddm-1.3.1.dist-info/WHEEL
iddm-1.3.1.dist-info/top_level.txt
iddm-1.3.1.dist-info/RECORD
