Metadata-Version: 2.4
Name: iddm
Version: 1.3.1
Summary: IDDM: Integrated Design Diffusion Model
Home-page: https://github.com/chairc/Integrated-Design-Diffusion-Model
Author: chairc
Author-email: chenyu1998424@gmail.com
License: Apache-2.0
Project-URL: Documentation, https://github.com/chairc/Integrated-Design-Diffusion-Model/blob/main/README.md
Project-URL: Source, https://github.com/chairc/Integrated-Design-Diffusion-Model
Project-URL: Tracker, https://github.com/chairc/Integrated-Design-Diffusion-Model/issues
Classifier: Programming Language :: Python :: 3
Classifier: Operating System :: OS Independent
Requires-Python: >=3.8
License-File: LICENSE
Requires-Dist: coloredlogs==15.0.1
Requires-Dist: gradio>=5.31.0
Requires-Dist: matplotlib==3.7.1
Requires-Dist: numpy>=1.25.0
Requires-Dist: Pillow==10.3.0
Requires-Dist: Requests>=2.32.4
Requires-Dist: scikit-image==0.22.0
Requires-Dist: torch_summary==1.4.5
Requires-Dist: tqdm==4.66.3
Requires-Dist: pytorch_fid==0.3.0
Requires-Dist: fastapi==0.115.6
Requires-Dist: tensorboard==2.19.0
Requires-Dist: tensorboardX==2.6.1
Requires-Dist: transformers==4.56.1
Requires-Dist: torch>=1.10.0
Requires-Dist: torchvision>=0.10.0
Dynamic: author
Dynamic: author-email
Dynamic: classifier
Dynamic: description
Dynamic: description-content-type
Dynamic: home-page
Dynamic: license
Dynamic: license-file
Dynamic: project-url
Dynamic: requires-dist
Dynamic: requires-python
Dynamic: summary
